README.txt
dlam.py
meigui.py
setup.py
turtlebhh.py
turtlebhm.py
zb.py
Chinapy.egg-info/PKG-INFO
Chinapy.egg-info/SOURCES.txt
Chinapy.egg-info/dependency_links.txt
Chinapy.egg-info/top_level.txt