Metadata-Version: 1.0
Name: Chinapy
Version: 0.100
Summary: 升级了Python常用库的代码，让代码写的更少，完成的功能更多。还有若干个模板，可以直接做成APP。
Home-page: UNKNOWN
Author: kenny2010525
Author-email: 3334652268@qq.com
License: UNKNOWN
Platform: UNKNOWN
